music_assistant/__init__.py
music_assistant/__main__.py
music_assistant/constants.py
music_assistant/logo.png
music_assistant/mass.py
music_assistant/py.typed
music_assistant/controllers/__init__.py
music_assistant/controllers/cache.py
music_assistant/controllers/config.py
music_assistant/controllers/metadata.py
music_assistant/controllers/music.py
music_assistant/controllers/player_queues.py
music_assistant/controllers/players.py
music_assistant/controllers/streams.py
music_assistant/controllers/webserver.py
music_assistant/controllers/media/__init__.py
music_assistant/controllers/media/albums.py
music_assistant/controllers/media/artists.py
music_assistant/controllers/media/audiobooks.py
music_assistant/controllers/media/base.py
music_assistant/controllers/media/playlists.py
music_assistant/controllers/media/podcasts.py
music_assistant/controllers/media/radio.py
music_assistant/controllers/media/tracks.py
music_assistant/helpers/__init__.py
music_assistant/helpers/api.py
music_assistant/helpers/app_vars.py
music_assistant/helpers/audio.py
music_assistant/helpers/auth.py
music_assistant/helpers/compare.py
music_assistant/helpers/database.py
music_assistant/helpers/datetime.py
music_assistant/helpers/dsp.py
music_assistant/helpers/ffmpeg.py
music_assistant/helpers/images.py
music_assistant/helpers/json.py
music_assistant/helpers/logging.py
music_assistant/helpers/playlists.py
music_assistant/helpers/podcast_parsers.py
music_assistant/helpers/process.py
music_assistant/helpers/scrobbler.py
music_assistant/helpers/tags.py
music_assistant/helpers/throttle_retry.py
music_assistant/helpers/upnp.py
music_assistant/helpers/uri.py
music_assistant/helpers/util.py
music_assistant/helpers/webserver.py
music_assistant/helpers/resources/announce.mp3
music_assistant/helpers/resources/fallback_fanart.jpeg
music_assistant/helpers/resources/logo.png
music_assistant/helpers/resources/silence.mp3
music_assistant/helpers/resources/silence_long.ogg
music_assistant/models/__init__.py
music_assistant-2.6.0.dist-info/licenses/LICENSE
music_assistant-2.6.0.dist-info/METADATA
music_assistant-2.6.0.dist-info/WHEEL
music_assistant-2.6.0.dist-info/entry_points.txt
music_assistant-2.6.0.dist-info/top_level.txt
music_assistant-2.6.0.dist-info/RECORD
