Metadata-Version: 2.4
Name: music_assistant
Version: 2.6.0
Summary: Music Assistant
Author-email: The Music Assistant Authors <marcelveldt@users.noreply.github.com>
License: Apache-2.0
Platform: any
Classifier: Environment :: Console
Classifier: Programming Language :: Python :: 3.12
Classifier: Programming Language :: Python :: 3.13
Requires-Python: >=3.12
License-File: LICENSE
Requires-Dist: aiodns>=3.2.0
Requires-Dist: aiohttp_asyncmdnsresolver==0.1.1
Requires-Dist: Brotli>=1.0.9
Requires-Dist: aiohttp==3.12.15
Requires-Dist: aiohttp-fast-zlib==0.3.0
Requires-Dist: aiofiles==24.1.0
Requires-Dist: aiorun==2025.1.1
Requires-Dist: aiosqlite==0.21.0
Requires-Dist: certifi==2025.7.14
Requires-Dist: colorlog==6.9.0
Requires-Dist: cryptography==45.0.6
Requires-Dist: chardet>=5.2.0
Requires-Dist: ifaddr==0.2.0
Requires-Dist: mashumaro==3.16
Requires-Dist: music-assistant-frontend==2.15.3
Requires-Dist: music-assistant-models==1.1.47
Requires-Dist: mutagen==1.47.0
Requires-Dist: orjson==3.11.3
Requires-Dist: pillow==11.3.0
Requires-Dist: podcastparser==0.6.10
Requires-Dist: propcache>=0.2.1
Requires-Dist: python-slugify==8.0.4
Requires-Dist: unidecode==1.4.0
Requires-Dist: xmltodict==0.14.2
Requires-Dist: shortuuid==1.0.13
Requires-Dist: zeroconf==0.147.0
Requires-Dist: uv>=0.8.0
Provides-Extra: test
Requires-Dist: codespell==2.4.1; extra == "test"
Requires-Dist: isort==6.0.1; extra == "test"
Requires-Dist: mypy==1.17.0; extra == "test"
Requires-Dist: pre-commit==4.2.0; extra == "test"
Requires-Dist: pre-commit-hooks==5.0.0; extra == "test"
Requires-Dist: pytest==8.4.1; extra == "test"
Requires-Dist: pytest-aiohttp==1.1.0; extra == "test"
Requires-Dist: pytest-cov==6.2.1; extra == "test"
Requires-Dist: syrupy==4.9.1; extra == "test"
Requires-Dist: tomli==2.2.1; extra == "test"
Requires-Dist: ruff==0.12.7; extra == "test"
Dynamic: license-file
